gitlint_rai/__init__.py
gitlint_rai/__main__.py
gitlint_rai/rules.py
gitlint_rai/version.py
gitlint_rai/sbom/sbom.cdx.json
gitlint_rai-0.1.6.dist-info/licenses/LICENSE
gitlint_rai-0.1.6.dist-info/METADATA
gitlint_rai-0.1.6.dist-info/WHEEL
gitlint_rai-0.1.6.dist-info/entry_points.txt
gitlint_rai-0.1.6.dist-info/top_level.txt
gitlint_rai-0.1.6.dist-info/RECORD
