Metadata-Version: 2.4
Name: gitlint-rai
Version: 0.1.6
Summary: Gitlint plugin for RAI footer validation
Author-email: Ashley Childress <human@checkmarkdevtools.dev>
License-Expression: LicenseRef-PolyForm-Shield-1.0.0
Project-URL: Homepage, https://github.com/ChecKMarKDevTools/rai-lint
Project-URL: Repository, https://github.com/ChecKMarKDevTools/rai-lint
Project-URL: Issues, https://github.com/ChecKMarKDevTools/rai-lint/issues
Keywords: gitlint,rai,ai-attribution,commit-validation
Classifier: Development Status :: 3 - Alpha
Classifier: Intended Audience :: Developers
Classifier: Operating System :: OS Independent
Classifier: Programming Language :: Python :: 3
Classifier: Programming Language :: Python :: 3.11
Classifier: Programming Language :: Python :: 3.12
Classifier: Topic :: Software Development :: Quality Assurance
Classifier: Topic :: Software Development :: Version Control :: Git
Classifier: Typing :: Typed
Requires-Python: <3.13,>=3.11
License-File: LICENSE
Requires-Dist: gitlint>=0.19.1
Dynamic: license-file
